{
  "@context": "http://schema.org",
  "@type": "Person",
  "id": "http://example.com/user/1",
  "name": {
    "@type": "Text",
    "firstName": "John",
    "lastName": "Doe"
  },
  "email": "mailto:john.doe@example.com",
  "image": "http://example.com/profiles/john.jpg",
  "description": "Hello, I'm John Doe!",
  "location": {
    "@type": "Place",
    "address": "New York, USA"
  },
  "skills": {
    "@type": "ItemList",
    "itemListElement": ["Programming", "Design", "Management"]
  },
  "memberOf": {
    "@type": "Organization",
    "name": "Tech Group",
    "description": "A tech-focused community group.",
    "member": "http://example.com/user/1"
  },
  "knowsAbout": ["Web Development", "AI", "Blockchain"],
  "owns": {
    "@type": "Product",
    "name": "Coordination App",
    "description": "An app for coordinating tasks and projects."
  },
  "worksFor": {
    "@type": "Organization",
    "name": "TechCorp",
    "employee": "http://example.com/user/1"
  },
  "hasCredential": {
    "@type": "EducationalOccupationalCredential",
    "name": "Certified Web Developer",
    "recognizedBy": "Tech Institute"
  }
}
